[{"year":2000,"hydro_elec_per_capita":956.202},{"year":2001,"hydro_elec_per_capita":729.112},{"year":2002,"hydro_elec_per_capita":886.387},{"year":2003,"hydro_elec_per_capita":918.107},{"year":2004,"hydro_elec_per_capita":884.272},{"year":2005,"hydro_elec_per_capita":888.552},{"year":2006,"hydro_elec_per_capita":943.076},{"year":2007,"hydro_elec_per_capita":794.766},{"year":2008,"hydro_elec_per_capita":813.033},{"year":2009,"hydro_elec_per_capita":871.344},{"year":2010,"hydro_elec_per_capita":818.49},{"year":2011,"hydro_elec_per_capita":996.984},{"year":2012,"hydro_elec_per_capita":856.747},{"year":2013,"hydro_elec_per_capita":826.238},{"year":2014,"hydro_elec_per_capita":786.221},{"year":2015,"hydro_elec_per_capita":751.646},{"year":2016,"hydro_elec_per_capita":798.05},{"year":2017,"hydro_elec_per_capita":890.988},{"year":2018,"hydro_elec_per_capita":862.949}]